{"name":"度量学习","slug":"度量学习","count":1,"postlist":[{"title":"DMLNet","uid":"cca6975b74b1218e11c5b9ba5de4d5ef","slug":"DMLNet","date":"2022-05-03T12:07:00.000Z","updated":"2022-05-04T06:39:34.572Z","comments":true,"path":"api/articles/DMLNet.json","keywords":null,"cover":[],"text":" 开放世界语义分割 开集语义分割模块 闭集语义分割子模块 异常分割子模块 增量小样本学习模块 我是短小精悍的文章摘要(๑•̀ㅂ•́) ✧ CODEmultiscale 是自己设定的吗 cfg.DATASET.imgSizes = (300, 375, 450, 525, 600) S...","link":"","photos":[],"count_time":{"symbolsCount":"12k","symbolsTime":"11 mins."},"categories":[],"tags":[{"name":"深度学习","slug":"深度学习","count":3,"path":"api/tags/深度学习.json"},{"name":"异常分割","slug":"异常分割","count":3,"path":"api/tags/异常分割.json"},{"name":"度量学习","slug":"度量学习","count":1,"path":"api/tags/度量学习.json"}],"author":{"name":"Star","slug":"blog-author","avatar":"https://gitee.com/zyxstar/Pic_bed/raw/master/image/C06BE6D9-B862-4B4B-A025-F273AE06FAF0.jpeg","link":"/","description":"有棱有角，还会发光；认真生活，星之煌煌","socials":{"github":"https://github.com/ZYXsmile","twitter":"","stackoverflow":"","wechat":"","qq":"","weibo":"","zhihu":"","csdn":"","juejin":"","customs":{}}}}]}